weather_wise/__init__.py
weather_wise/data/2024_Gaz_zcta_national.csv
weather_wise/data/2024_Gaz_zcta_national.json
weather_wise/data/2024_Gaz_zcta_national.txt
weather_wise/data/archive/2022_gazetteer_zcta_national.json
weather_wise/data/archive/2022_gazetteer_zcta_national.txt
weather_wise/utils/convert_zcta_csv_to_json.py
weather_wise/weather_wise.py
weather_wise-0.1.9.dist-info/METADATA
weather_wise-0.1.9.dist-info/WHEEL
weather_wise-0.1.9.dist-info/RECORD
