Metadata-Version: 2.1
Name: weather-wise
Version: 0.1.9
Summary: Obtain local weather information based on zipcode.
Author: Aaron Britton
Author-email: brittonleeaaron@gmail.com
Requires-Python: >=3.12,<4.0
Classifier: Programming Language :: Python :: 3
Classifier: Programming Language :: Python :: 3.12
Classifier: Programming Language :: Python :: 3.13
Requires-Dist: mkdocs (>=1.6.1,<2.0.0)
Requires-Dist: mkdocs-material (>=9.6.9,<10.0.0)
Requires-Dist: pandas (>=2.2.3,<3.0.0)
Requires-Dist: requests (>=2.28.1,<3.0.0)
